xia_meta_secret/__init__.py
xia_meta_secret/secrets.cp39-win_amd64.pyd
xia_meta_secret-0.1.2.dist-info/LICENSE.txt
xia_meta_secret-0.1.2.dist-info/METADATA
xia_meta_secret-0.1.2.dist-info/WHEEL
xia_meta_secret-0.1.2.dist-info/top_level.txt
xia_meta_secret-0.1.2.dist-info/RECORD
